[
  {
    "title": "iceland",
    "prettyTitle": "Iceland",
    "posterImg": "https://lh3.googleusercontent.com/drive-viewer/AFGJ81rKAye40HRSC_SubLocBcDL_eQyGSIfiQhZ034t147okY0EcFaOBDaIK8gNpG9ecMERBWKrr7r_jU9x2Pe7fHjvac630w=s1600",
    
    "posterVid": "",
    "categories": [
      "travel"
    ],
    "album": [
      {
        "title": "reflection",
        "thumbUrl": "https://lh3.googleusercontent.com/drive-viewer/AFGJ81ooQiIiDNJNIsGHnS254mFsleEGlty3dDLTKCYBjh2tGxRCfk4gVepRAvSBsrLvc3Gq91JIfC6Un3Vo6PVEnDHG2mH3Hg=s1600",
        "posterUrl": "https://lh3.googleusercontent.com/drive-viewer/AFGJ81qcVAiJ0Pm_w2Bd_yb-bFcgUWq4wIRMPRFX2y9sMWb0_q8Xb4uvuzgfWk1aa6dV96f3jTcfI0pWHEA7UYUtMS4TsWXJEQ=s1600",
        "videoUrl": "",
        "categories": [
          "landscape"
        ],
        "tags": [
          "purple",
          "sunset",
          "mirror",
          "reflection",
          "mountain",
          "ice",
          "cold",
          "water"
        ]
      },
      {
        "title": "temp-40",
        "thumbUrl": "/photo/iceland/temp/C0074_vertical_poster_03.jpg",
        "posterUrl": "/photo/iceland/temp/C0074_vertical_poster_03.jpg",
        "videoUrl": "/photo/iceland/temp/C0074_vertical_05.mp4",
        "categories": [
          ""
        ],
        "tags": [
          ""
        ],
        "orientation": "vertical"
      },
      {
        "title": "temp-14",
        "thumbUrl": "/photo/iceland/temp/Wires_v002_temp_HD_04.jpg",
        "posterUrl": "/photo/iceland/temp/DSC05986_temp_HD.jpg",
        "videoUrl": "",
        "categories": [
          "landscape"
        ],
        "tags": [
          "blah",
          "blahblah",
          "blahblahblah"
        ],
        "orientation": "vertical"
      },
      {
        "title": "temp-27",
        "thumbUrl": "/photo/iceland/temp/DSC07978_temp_HD.jpg",
        "posterUrl": "/photo/iceland/temp/DSC07978_temp_HD.jpg",
        "videoUrl": "",
        "categories": [
          ""
        ],
        "tags": [
          ""
        ]
      },
      {
        "title": "temp-22",
        "thumbUrl": "/photo/iceland/temp/C0089_vertical_poster.jpg",
        "posterUrl": "/photo/iceland/temp/DSC08121_temp_HD.jpg",
        "videoUrl": "/photo/iceland/temp/C0089_vertical.mp4",
        "categories": [
          ""
        ],
        "tags": [
          ""
        ],
        "orientation": "vertical"
      },
      {
        "title": "temp-40s",
        "thumbUrl": "/photo/iceland/temp/DSC06197_temp_HD.jpg",
        "posterUrl": "/photo/iceland/temp/DSC06197_temp_HD.jpg",
        "videoUrl": "",
        "categories": [
          ""
        ],
        "tags": [
          ""
        ],
        "orientation": "vertical"
      },
      {
        "title": "temp-59",
        "thumbUrl": "/photo/iceland/temp/C0116_HD_poster.jpg",
        "posterUrl": "/photo/iceland/temp/C0116_HD_poster.jpg",
        "videoUrl": "/photo/iceland/temp/C0116_HD.mp4",
        "categories": [
          ""
        ],
        "tags": [
          ""
        ],
        "position": "special"
      },
      {
        "title": "temp-21s",
        "thumbUrl": "/photo/iceland/temp/C0024_HD_poster.jpg",
        "posterUrl": "/photo/iceland/temp/C0024_HD_poster.jpg",
        "videoUrl": "/photo/iceland/temp/C0024_HD.mp4",
        "categories": [
          ""
        ],
        "tags": [
          ""
        ]
      },
     
      
      {
        "title": "temp-18",
        "thumbUrl": "/photo/iceland/temp/DSC06446_temp_HD.jpg",
        "posterUrl": "/photo/iceland/temp/DSC06446_temp_HD.jpg",
        "videoUrl": "",
        "categories": [
          ""
        ],
        "tags": [
          ""
        ]
      },
      
     
     
      {
        "title": "temp-21",
        "thumbUrl": "/photo/iceland/temp/DSC07385_temp_HD.jpg",
        "posterUrl": "/photo/iceland/temp/DSC07385_temp_HD.jpg",
        "videoUrl": "",
        "categories": [
          ""
        ],
        "tags": [
          ""
        ]
      },
      {
        "title": "temp-33",
        "thumbUrl": "/photo/iceland/temp/DSC08059_temp_HD.jpg",
        "posterUrl": "/photo/iceland/temp/DSC08059_temp_HD.jpg",
        "videoUrl": "",
        "categories": [
          ""
        ],
        "tags": [
          ""
        ],
        "orientation": "vertical"
      },
      {
        "title": "temp-32",
        "thumbUrl": "/photo/iceland/temp/DSC08092_temp_HD.jpg",
        "posterUrl": "/photo/iceland/temp/DSC08092_temp_HD.jpg",
        "videoUrl": "",
        "categories": [
          ""
        ],
        "tags": [
          ""
        ],
        "orientation": "vertical"
      },
      {
        "title": "temp-06",
        "thumbUrl": "/photo/iceland/temp/DSC07936_temp_HD.jpg",
        "posterUrl": "/photo/iceland/temp/DSC07936_temp_HD.jpg",
        "videoUrl": "",
        "categories": [
          ""
        ],
        "tags": [
          ""
        ],
        "orientation": "vertical"
      },
      {
        "title": "temp-35",
        "thumbUrl": "/photo/iceland/temp/DSC08263_temp_HD.jpg",
        "posterUrl": "/photo/iceland/temp/DSC08263_temp_HD.jpg",
        "videoUrl": "",
        "categories": [
          ""
        ],
        "tags": [
          ""
        ],
        "orientation": "vertical"
      }
    ]
  },
  
  {
    "title": "france",
    "prettyTitle": "France",
    "posterImg": "/photo/france/temp/DSC02130b.jpg",
    "posterVid": "",
    "categories": [
      "travel"
    ],
    
    "album": [
      
      {
        "title": "three",
        "thumbUrl": "/photo/france/temp/DSC01486d.jpg",
        "posterUrl": "/photo/france/temp/DSC01486d.jpg",
        "categories": [
          ""
        ],
        "tags": [
          ""
        ]
      },
      {
        "title": "three",
        "thumbUrl": "/photo/france/temp/DSC02130b.jpg",
        "posterUrl": "/photo/france/temp/DSC02130b.jpg",
        "categories": [
          ""
        ],
        "tags": [
          ""
        ]
      },
      {
        "title": "three",
        "thumbUrl": "/photo/france/temp/DSC01674.jpg",
        "posterUrl": "/photo/france/temp/DSC01674.jpg",
        "categories": [
          ""
        ],
        "tags": [
          ""
        ],
        "orientation": "vertical"
      },
      {
        "title": "one",
        "thumbUrl": "/photo/france/temp/DSC01701b.jpg",
        "posterUrl": "/photo/france/temp/DSC01701b.jpg",
        "categories": [
          ""
        ],
        "tags": [
          ""
        ],
        "orientation": "vertical"
      },
      {
        "title": "three",
        "thumbUrl": "/photo/france/temp/DSC01349.jpg",
        "posterUrl": "/photo/france/temp/DSC01349.jpg",
        "categories": [
          ""
        ],
        "tags": [
          ""
        ]
      },
      {
        "title": "one",
        "thumbUrl": "/photo/france/temp/DSC01833.jpg",
        "posterUrl": "/photo/france/temp/DSC01833.jpg",
        "categories": [
          ""
        ],
        "tags": [
          ""
        ],
        "orientation": "vertical"
      },
      {
        "title": "one",
        "thumbUrl": "/photo/france/temp/DSC01831.jpg",
        "posterUrl": "/photo/france/temp/DSC01831.jpg",
        "categories": [
          ""
        ],
        "tags": [
          ""
        ],
        "orientation": "vertical"
      },
      {
        "title": "three",
        "thumbUrl": "/photo/france/temp/DSC01818.jpg",
        "posterUrl": "/photo/france/temp/DSC01818.jpg",
        "categories": [
          ""
        ],
        "tags": [
          ""
        ]
      },

      {
        "title": "one",
        "thumbUrl": "/photo/france/temp/DSC00473.jpg",
        "posterUrl": "/photo/france/temp/DSC00473.jpg",
        "categories": [
          ""
        ],
        "tags": [
          ""
        ]
      },
      {
        "title": "one",
        "thumbUrl": "/photo/france/temp/DSC00825.jpg",
        "posterUrl": "/photo/france/temp/DSC00825.jpg",
        "categories": [
          ""
        ],
        "tags": [
          ""
        ],
        "orientation": "vertical"
      },
      {
        "title": "three",
        "thumbUrl": "/photo/france/temp/DSC00493.jpg",
        "posterUrl": "/photo/france/temp/DSC00493.jpg",
        "categories": [
          ""
        ],
        "tags": [
          ""
        ],
        "orientation": "vertical"
      },
      {
        "title": "one",
        "thumbUrl": "/photo/france/temp/DSC00674.jpg",
        "posterUrl": "/photo/france/temp/DSC00674.jpg",
        "categories": [
          ""
        ],
        "tags": [
          ""
        ],
        "orientation": "vertical"
      },
      {
        "title": "one",
        "thumbUrl": "/photo/france/temp/DSC00690.jpg",
        "posterUrl": "/photo/france/temp/DSC00690.jpg",
        "categories": [
          ""
        ],
        "tags": [
          ""
        ],
        "orientation": "vertical"
      },
      {
        "title": "three",
        "thumbUrl": "/photo/france/temp/DSC01372.jpg",
        "posterUrl": "/photo/france/temp/DSC01372.jpg",
        "categories": [
          ""
        ],
        "tags": [
          ""
        ]
      }
    ]
  },
  {
    "title": "forest",
    "prettyTitle": "Forest",
    "posterImg": "/photo/forest/C0176.jpg",
    "posterVid": "",
    "categories": [
      ""
    ],
    "album": [
      {
        "title": "reflection",
        "thumbUrl": "/photo/forest/C0176.jpg",
        "posterUrl": "/photo/forest/C0176.jpg",
        "videoUrl": "/photo/forest/C0176.mp4",
        "categories": [
          "landscape"
        ],
        "tags": [
          "purple",
          "sunset",
          "mirror",
          "reflection",
          "mountain",
          "ice",
          "cold",
          "water"
        ]
      },
      {
        "title": "refslection",
        "thumbUrl": "/photo/forest/C0176_poster.jpg",
        "posterUrl": "/photo/forest/C0176_poster.jpg",
        "videoUrl": "/photo/forest/C0217.mp4",
        "categories": [
          "landscape"
        ],
        "tags": [
          "purple",
          "sunset",
          "mirror",
          "reflection",
          "mountain",
          "ice",
          "cold",
          "water"
        ]
      }
    ]
  },
  {
    "title": "tanzania",
    "prettyTitle": "Tanzania",
    "posterImg": "/photo/tanzania/giraffe/giraffe_thumb.jpg",
    "posterVid": "",
    "categories": [
      "travel"
    ],
    
    "album": [
      {
        "title": "giraffe",
        "thumbUrl": "/photo/tanzania/giraffe/giraffe_thumb.jpg",
        "posterUrl": "/photo/tanzania/giraffe/giraffe.jpg",
        "categories": [
          "animals"
        ],
        "tags": [
          "blah",
          "blahblah",
          "blahblahblah"
        ]
      },
      
      {
        "title": "protection",
        "thumbUrl": "/photo/tanzania/protection/protection_thumb.jpg",
        "posterUrl": "/photo/tanzania/protection/protection.jpg",
        "categories": [
          "animals"
        ],
        "tags": [
          "blah",
          "blahblah",
          "blahblahblah"
        ]
      },
      {
        "title": "hippo-yelling",
        "thumbUrl": "/photo/tanzania/hippo-yelling/hippo-yelling_thumb.jpg",
        "posterUrl": "/photo/tanzania/hippo-yelling/hippo-yelling.jpg",
        "categories": [
          "animals"
        ],
        "tags": [
          "blah",
          "blahblah",
          "blahblahblah"
        ]
      },
      
      

      {
        "title": "wildebeest2",
        "thumbUrl": "/photo/tanzania/temp/Serengeti & Wild Camp 544.JPG",
        "posterUrl": "/photo/tanzania/temp/Serengeti & Wild Camp 544.JPG",
        "categories": [
          "animals"
        ],
        "tags": [
          "blah",
          "blahblah",
          "blahblahblah"
        ],
        "orientation": "vertical"
      },
      {
        "title": "wildebeest2",
        "thumbUrl": "/photo/tanzania/temp/Lake Manyara 229.JPG",
        "posterUrl": "/photo/tanzania/temp/Lake Manyara 229.JPG",
        "categories": [
          "animals"
        ],
        "tags": [
          "blah",
          "blahblah",
          "blahblahblah"
        ],
        "orientation": "vertical"
      },
      {
        "title": "lion",
        "thumbUrl": "/photo/tanzania/lion/lion_thumb.jpg",
        "posterUrl": "/photo/tanzania/lion/lion.jpg",
        "categories": [
          "animals"
        ],
        "tags": [
          "blah",
          "blahblah",
          "blahblahblah"
        ]
      },
      {
        "title": "lean-on-me",
        "thumbUrl": "/photo/tanzania/temp/Serengeti & Wild Camp 335.JPG",
        "posterUrl": "/photo/tanzania/temp/Serengeti & Wild Camp 335.JPG",
        "categories": [
          "animals"
        ],
        "tags": [
          "blah",
          "blahblah",
          "blahblahblah"
        ]
      },
      
     
     
      
     
    
     
      
     
      {
        "title": "wildebeest2",
        "thumbUrl": "/photo/tanzania/temp/Ngorongoro & Børnehjem 018.JPG",
        "posterUrl": "/photo/tanzania/temp/Ngorongoro & Børnehjem 018.JPG",
        "categories": [
          "animals"
        ],
        "tags": [
          "blah",
          "blahblah",
          "blahblahblah"
        ],
        "position": "special"
      },
     
    
     
      {
        "title": "wildebeest1",
        "thumbUrl": "/photo/tanzania/temp/IMG_8351.JPG",
        "posterUrl": "/photo/tanzania/temp/IMG_8351.JPG",
        "categories": [
          "animals"
        ],
        "tags": [
          "blah",
          "blahblah",
          "blahblahblah"
        ],
        "orientation": "vertical"
      },
     
      {
        "title": "wildebeest1",
        "thumbUrl": "/photo/tanzania/temp/IMG_8353.JPG",
        "posterUrl": "/photo/tanzania/temp/IMG_8353.JPG",
        "categories": [
          "animals"
        ],
        "tags": [
          "blah",
          "blahblah",
          "blahblahblah"
        ],
        "orientation": "vertical"
      },
      {
        "title": "giraffes",
        "thumbUrl": "/photo/tanzania/giraffes/giraffes_thumb.jpg",
        "posterUrl": "/photo/tanzania/giraffes/giraffes.jpg",
        "categories": [
          "animals"
        ],
        "tags": [
          "blah",
          "blahblah",
          "blahblahblah"
        ],
        "position": "special"
      },
     
      {
        "title": "wildebeest",
        "thumbUrl": "/photo/tanzania/wildebeest/wildebeest_thumb.jpg",
        "posterUrl": "/photo/tanzania/wildebeest/wildebeest.jpg",
        "categories": [
          "animals"
        ],
        "tags": [
          "blah",
          "blahblah",
          "blahblahblah"
        ]
      }
    ]
  }
]
